pylicenser-0.0.13.dist-info/WHEEL
pylicenser-0.0.13.dist-info/METADATA
pylicenser-0.0.13.dist-info/entry_points.txt
pylicenser-0.0.13.dist-info/top_level.txt
pylicenser-0.0.13.dist-info/RECORD
pylicenser/utils.cpython-38-x86_64-linux-gnu.so
pylicenser/script.cpython-38-x86_64-linux-gnu.so
pylicenser/__init__.py
pylicenser/VERSION
pylicenser/monitor.cpython-38-x86_64-linux-gnu.so
pylicenser/cy.cpython-38-x86_64-linux-gnu.so
pylicenser/_excepts.cpython-38-x86_64-linux-gnu.so
pylicenser/encrypt.cpython-38-x86_64-linux-gnu.so
pylicenser/decrypt.cpython-38-x86_64-linux-gnu.so
pylicenser/license/__init__.py
pylicenser/license/_crypto.cpython-38-x86_64-linux-gnu.so
pylicenser/license/_compiler.cpython-38-x86_64-linux-gnu.so
pylicenser/license/loader.cpython-38-x86_64-linux-gnu.so
pylicenser/license/_cipher.cpython-38-x86_64-linux-gnu.so
pylicenser-0.0.13.data/data/VERSION
