Metadata-Version: 2.1
Name: pylicenser
Version: 0.0.13
Summary: 代码混淆
Home-page: UNKNOWN
Author: blair
Author-email: tech@bailian.ai
License: UNKNOWN
Project-URL: Source, https://gitlab.bailian-ai.com/ai_algo/pylicenser
Keywords: encrypt,pylicenser
Platform: UNKNOWN
Classifier: Development Status :: 3 - Alpha
Classifier: Intended Audience :: Developers
Classifier: Topic :: Software Development :: Build Tools
Classifier: License :: OSI Approved :: MIT License
Classifier: Programming Language :: Python :: 3.6
Classifier: Programming Language :: Python :: 3.7
Classifier: Programming Language :: Python :: 3.8
Requires-Python: >=3.6, <4
Requires-Dist: pycryptodome
Requires-Dist: regex
Requires-Dist: Cython
Provides-Extra: dev
Provides-Extra: test
Requires-Dist: pytest ; extra == 'test'
